README.md
setup.py
vidfetch/__init__.py
vidfetch.egg-info/PKG-INFO
vidfetch.egg-info/SOURCES.txt
vidfetch.egg-info/dependency_links.txt
vidfetch.egg-info/requires.txt
vidfetch.egg-info/top_level.txt
vidfetch/api/__init__.py
vidfetch/api/huggingface.py
vidfetch/package/__init__.py
vidfetch/package/youtube_dl.py
vidfetch/uid/base.py
vidfetch/uid/mixkit.py
vidfetch/uid/pexels.py
vidfetch/uid/pixabay.py
vidfetch/utils/__init__.py
vidfetch/utils/driver.py
vidfetch/utils/file.py
vidfetch/utils/view_source.py
vidfetch/video/__init__.py
vidfetch/video/data.py
vidfetch/video/dataset.py
vidfetch/video/monitor.py
vidfetch/website/__init__.py
vidfetch/website/mixkit.py
vidfetch/website/pexels.py
vidfetch/website/pexels_api.py
vidfetch/website/pixabay.py