Metadata-Version: 2.1
Name: vidfetch
Version: 0.0.1a1
Summary: data4co provides convenient dataset generators for the combinatorial optimization problem
Home-page: https://github.com/heatingma/VidFetch/
Author: heatingma
License: Mulan PSL v2
Classifier: License :: OSI Approved :: Mulan Permissive Software License v2 (MulanPSL-2.0)
Classifier: Programming Language :: Python
Classifier: Programming Language :: Python :: 3
Classifier: Programming Language :: Python :: 3.8
Classifier: Programming Language :: Python :: 3.9
Classifier: Programming Language :: Python :: 3.10
Classifier: Programming Language :: Python :: 3 :: Only
Classifier: Programming Language :: Python :: Implementation :: CPython
Classifier: Operating System :: Microsoft :: Windows
Classifier: Operating System :: POSIX
Classifier: Operating System :: Unix
Classifier: Operating System :: MacOS
Classifier: Environment :: Console
Classifier: Topic :: Scientific/Engineering :: Artificial Intelligence
Classifier: Topic :: Scientific/Engineering :: Image Recognition
Classifier: Topic :: Scientific/Engineering :: Mathematics
Requires-Python: >=3.8
Requires-Dist: aiohttp>=3.9.3
Requires-Dist: async_timeout>=4.0.3
Requires-Dist: tqdm>=4.66.2
Requires-Dist: texttable>=1.7.0
Requires-Dist: moviepy>=1.0.3
Requires-Dist: bs4>=0.0.2
Requires-Dist: selenium>=4.18.1
Requires-Dist: requests>=2.31.0
Requires-Dist: texttable>=1.7.0
Requires-Dist: huggingface_hub>=0.22.2
